xaspy/__init__.py
xaspy/beamlines/__init__.py
xaspy/beamlines/bl631.py
xaspy/readin/PiMoss.py
xaspy/readin/__init__.py
xaspy/readin/bl631.py
xaspy/readin/theory.py
xaspy/readin/vekmag.py
xaspy/utils/__init__.py
xaspy/utils/despike.py
xaspy/utils/p65_add_to_xdi.py
xaspy/utils/p65_recovery.py
xaspy/utils/split.py
xaspy/utils/utils.py
xaspy/xas/__init__.py
xaspy/xas/backgrounds.py
xaspy/xas/polarized.py
xaspy/xas/xas.py
xaspy-0.3.9.dist-info/licenses/LICENSE
xaspy-0.3.9.dist-info/METADATA
xaspy-0.3.9.dist-info/WHEEL
xaspy-0.3.9.dist-info/top_level.txt
xaspy-0.3.9.dist-info/RECORD
