Metadata-Version: 2.4
Name: xaspy
Version: 0.3.9
Summary: Package for analysis of experimental xray absorption spectroscopy data
Author: Damian Guenzing, Alpha T. N'Diaye
Maintainer-email: Damian Guenzing <dguenzing@lbl.gov>
License-Expression: MIT
Project-URL: Homepage, https://github.com/gnzng/xaspy
Keywords: xray absorption spectroscopy,xmcd,synchrotron
Requires-Python: >=3.10
License-File: LICENSE
Requires-Dist: numpy
Requires-Dist: pandas
Requires-Dist: scipy
Requires-Dist: matplotlib
Requires-Dist: pytest
Dynamic: license-file
